d3_scripts/build_type_map.py
d3_scripts/check_behaviours_resolve.py
d3_scripts/check_uri_resolve.py
d3_scripts/claim_graph.py
d3_scripts/cpe_tools.py
d3_scripts/d3_build.py
d3_scripts/d3_build_db.py
d3_scripts/d3_build_malicious_behaviours.py
d3_scripts/d3_build_vulnerabilities.py
d3_scripts/d3_cli.py
d3_scripts/d3_constants.py
d3_scripts/d3_lint.py
d3_scripts/d3_populate.py
d3_scripts/d3_to_markdown.py
d3_scripts/d3_utils.py
d3_scripts/export_tools.py
d3_scripts/guid.py
d3_scripts/guid_tools.py
d3_scripts/json_tools.py
d3_scripts/resolve_behaviour_rules.py
d3_scripts/schemas/README.md
d3_scripts/schemas/behaviour.json
d3_scripts/schemas/d3-claim.json
d3_scripts/schemas/firmware.json
d3_scripts/schemas/instance.json
d3_scripts/schemas/type.json
d3_scripts/schemas/vuln.json
d3_scripts/schemas/vulnerability.json
d3_scripts/theme/static/css/banner.css
d3_scripts/theme/static/css/list-item.css
d3_scripts/theme/static/css/style.css
d3_scripts/theme/templates/base.html
d3_scripts/validate_schemas.py
d3_scripts/website_builder.py
d3_scripts/write_pelican_config.py
d3_scripts/yaml_tools.py
d3_cli-0.2.5.dist-info/entry_points.txt
d3_cli-0.2.5.dist-info/WHEEL
d3_cli-0.2.5.dist-info/METADATA
d3_cli-0.2.5.dist-info/RECORD
