Metadata-Version: 2.1
Name: d3-cli
Version: 0.2.5
Summary: Utility scripts for ManySecured-D3 claims
Home-page: https://github.com/TechWorksHub/ManySecured-D3DB
Author: NquiringMinds
Author-email: contact@nquiringminds.com
Requires-Python: >=3.8,<4
Classifier: Programming Language :: Python :: 3
Classifier: Programming Language :: Python :: 3.8
Classifier: Programming Language :: Python :: 3.9
Classifier: Programming Language :: Python :: 3.10
Classifier: Programming Language :: Python :: 3.11
Requires-Dist: PyYAML (>=6.0,<7.0)
Requires-Dist: bidict (>=0.22.0,<0.23.0)
Requires-Dist: ipython (>=8.4.0,<9.0.0)
Requires-Dist: iteration-utilities (>=0.11.0,<0.12.0)
Requires-Dist: jsonschema (>=4.4.0,<5.0.0)
Requires-Dist: markdown (>=3.4.1,<4.0.0)
Requires-Dist: matplotlib (>=3.5.2,<4.0.0)
Requires-Dist: networkx (>=2.8.3,<3.0.0)
Requires-Dist: pandas (>=1.4.2,<2.0.0)
Requires-Dist: pelican (>=4.8.0,<5.0.0)
Requires-Dist: pelican-graphviz (>=1.2.2,<2.0.0)
Requires-Dist: requests (>=2.27.1,<3.0.0)
Requires-Dist: tabulate (>=0.9.0,<0.10.0)
Requires-Dist: tqdm (>=4.64.0,<5.0.0)
Requires-Dist: yamllint (>=1.26.3,<2.0.0)
Project-URL: Repository, https://github.com/TechWorksHub/ManySecured-D3DB.git
